LICENSE.txt
README.md
setup.cfg
setup.py
Topsis_102116120/__init__.py
Topsis_102116120/main.py
Topsis_102116120.egg-info/PKG-INFO
Topsis_102116120.egg-info/SOURCES.txt
Topsis_102116120.egg-info/dependency_links.txt
Topsis_102116120.egg-info/requires.txt
Topsis_102116120.egg-info/top_level.txt